pixelblaze/__init__.py
pixelblaze/pixelblaze.py
pixelblaze_client-1.1.7.dist-info/licenses/LICENSE.md
pixelblaze_client-1.1.7.dist-info/METADATA
pixelblaze_client-1.1.7.dist-info/WHEEL
pixelblaze_client-1.1.7.dist-info/entry_points.txt
pixelblaze_client-1.1.7.dist-info/top_level.txt
pixelblaze_client-1.1.7.dist-info/RECORD
