Metadata-Version: 2.4
Name: pixelblaze-client
Version: 1.1.7
Summary: Library for Pixelblaze addressable LED controller.
Home-page: https://github.com/zranger1/pixelblaze-client
Author: pixelblaze-client team
License: MIT
Keywords: pixelblaze
Classifier: Development Status :: 5 - Production/Stable
Classifier: License :: OSI Approved :: MIT License
Classifier: Programming Language :: Python :: 3
Classifier: Operating System :: OS Independent
Classifier: Topic :: Software Development :: Libraries :: Python Modules
Classifier: Topic :: System :: Hardware
Classifier: Intended Audience :: Developers
Requires-Python: >=3.9
License-File: LICENSE.md
Requires-Dist: websocket-client
Requires-Dist: requests
Requires-Dist: pytz
Requires-Dist: mini-racer
Requires-Dist: click>=8.0
Requires-Dist: json5
Requires-Dist: lzstring
Dynamic: author
Dynamic: classifier
Dynamic: description
Dynamic: description-content-type
Dynamic: home-page
Dynamic: keywords
Dynamic: license
Dynamic: license-file
Dynamic: requires-dist
Dynamic: requires-python
Dynamic: summary
